{
	"plugins": [
		{
			"name": "Essentials",
			"desc": "Essential commands\n&aAll Essentials plugins count as 1 plugin.",
			"jarName": "Essentials.jar",
			"configName": "Essentials"
		},
		{
			"name": "Essentials Spawn",
			"desc": "Setup a server spawn point.\n&aAll Essentials plugins count as 1 plugin.",
			"jarName": "EssentialsSpawn.jar",
			"configName": "~"
		},
		{
			"name": "Essentials Chat",
			"desc": "Format the chat to make it look nicer.\n&aAll Essentials plugins count as 1 plugin.",
			"jarName": "EssentialsChat.jar",
			"configName": "~"
		},
		{
			"name": "Essentials Kit Adder",
			"desc": "Add kits with commands\n&aAll Essentials plugins count as 1 plugin.",
			"jarName": "KitAdder.jar",
			"configName": "KitAdder"
		},
		{
			"name": "Essentials Group Manager",
			"desc": "Create permission systems.\n&aAll Essentials plugins count as 1 plugin.",
			"jarName": "GroupManager.jar",
			"configName": "GroupManager"
		},
		{
			"name": "Permissions Ex",
			"desc": "Create permission systems.",
			"jarName": "PermissionsEx.jar",
			"configName": "PermissionsEx"
		},
		{
			"name": "No Cheat Plus",
			"desc": "Anti-cheat system to block bad modifications. \n&aProtocolLib is &a&nrecommended&r&a while using No Cheat Plus.",
			"jarName": "NoCheatPlus.jar",
			"configName": "NoCheatPlus"
		},
		{
			"name": "World Edit",
			"desc": "Build tools.",
			"jarName": "worldedit.jar",
			"configName": "WorldEdit"
		},
		{
			"name": "Fast Async WorldEdit",
			"desc": "Extremely optimized WorldEdit to use when working with big numbers.",
			"jarName": "FastAsyncWorldEdit.jar",
			"configName": "FastAsyncWorldEdit"
		},
		{
			"name": "AsyncWorldEdit",
			"desc": "WorldEdit with reduced lag.\n&cRequires &nWorldEdit&c and &nAsyncWorldEditInjector&r&c to be installed.",
			"jarName": "AsyncWorldEdit.jar",
			"configName": "AsyncWorldEdit",
			"disabled": true
		},
		{
			"name": "AsyncWorldEditInjector",
			"desc": "Required plugin for &nAsyncWorldEdit&r",
			"jarName": "AsyncWorldEditInjector.jar",
			"configName": "AsyncWorldEditInjector",
			"disabled": true
		},
		{
			"name": "World Guard",
			"desc": "Create and manage regions using this plugin.",
			"jarName": "worldguard.jar",
			"configName": "WorldGuard"
		},
		{
			"name": "Vault",
			"desc": "Economy API.",
			"jarName": "Vault.jar",
			"configName": "Vault"
		},
		{
			"name": "ProtocolLib",
			"desc": "Allows plugins to access new functions.",
			"jarName": "ProtocolLib.jar",
			"configName": "ProtocolLib"
		},
		{
			"name": "ChestShop",
			"desc": "Chestshops that allow players to sell/buy items.",
			"jarName": "ChestShop.jar",
			"configName": "ChestShop"
		},
		{
			"name": "Crack Shot",
			"desc": "Guns in Minecraft.",
			"jarName": "CrackShot.jar",
			"configName": "CrackShot"
		},
		{
			"name": "Crates Plus",
			"desc": "Crates to give out rewards to players with keys.",
			"jarName": "CratesPlus.jar",
			"configName": "CratesPlus"
		},
		{
			"name": "Shopkeepers",
			"desc": "Create customizable villager shops with this plugin.",
			"jarName": "Shopkeepers.jar",
			"configName": "Shopkeepers"
		},
		{
			"name": "Silk Spawners",
			"desc": "Create and pick up custom mob spawners.",
			"jarName": "SilkSpawners.jar",
			"configName": "SilkSpawners"
		},
		{
			"name": "MineResetLite",
			"desc": "Create mines that will reset.",
			"jarName": "MineResetLite.jar",
			"configName": "MineResetLite"
		},
		{
			"name": "AntiSwear",
			"desc": "Stop players spamming & cussing in chat.",
			"jarName": "AntiSwear.jar",
			"configName": "ChatControl"
		},
		{
			"name": "Lockette",
			"desc": "Personal chest protection system.",
			"jarName": "Lockette.jar",
			"configName": "Lockette"
		},
		{
			"name": "EZRanksLite",
			"desc": "Simple auto rankup plugin.\n&cRequires Vault and a permissions plugin.\n&cScoreboards will reset when installed.",
			"jarName": "EZRanksLite1.6-Bukkit-1.8.jar",
			"configName": "EZRanksLite1.6-Bukkit-1.8"
		},
{
			"name": "Combat Log",
			"desc": "Punish players who log out during combat!",
			"jarName": "CombatLog-1.8.11-fix.jar",
			"configName": "CombatLog-1.8.11-fix"
		},
		{
			"name": "Libs Disguises",
			"desc": "Disguise as mobs!\n&cRequires &nProtocolLib&r",
			"jarName": "LibsDisguises.jar",
			"configName": "LibsDisguises"
		},
		{
			"name": "Create Your Own Menus",
			"desc": "Allows you to create your own GUI menus!",
			"jarName": "CreateYourOwnMenus-0.5.9.jar",
			"configName": "CreateYourOwnMenus"
		},
		{	
			"name": "EchoPet",
			"desc": "EchoPet is no longer supported for 1.9+. It will not work!",
			"jarName": "EchoPet_v2.8.0.jar",
			"configName": "EchoPet_v2.8.0",
			"disabled": true
		},
		{
		    "name": "SonarPet",
			"desc": "A fork of EchoPet updated for 1.9.",
			"jarName": "SonarPet.jar",
			"configName": "SonarPet"
		},
		{
			"name": "ObsidianAuctions",
			"desc": "Unique chat based auction system.\n&cThis plugin requires &nVault&c.",
			"jarName": "ObsidianAuctions.jar",
			"configName": "ObsidianAuctions"
		},
		{
			"name": "VoxelSniper",
			"desc": "Long range map editing tool for terraforming.",
			"jarName": "VoxelSniper-7.1.0-SNAPSHOT-all.jar",
			"configName": "VoxelSniper"
		},
		{
			"name": "BetterCombat",
			"desc": "Moves the combat style back to 1.7/1.8\nRemoves attack speed, adds block hitting, etc.",
			"jarName": "BetterCombat.jar",
			"configName": "BetterCombat"
		},
		{
			"name": "Easy Trades",
			"desc": "Lets players easily and safely trade items via a GUI.",
			"jarName": "EasyTrades.jar",
			"configName": "EasyTrades"
		},
		{
			"name": "Action Announcer",
			"desc": "Create timed broadcasts for your server through the action bar.",
			"jarName": "ActionAnnouncer.jar",
			"configName": "ActionAnnouncer"
		},
		{
			"name": "Holographic Displays",
			"desc": "Make floating messages around your world.",
			"jarName": "HolographicDisplays.jar",
			"configName": "HolographicDisplays"
		},
		{
			"name": "SuperTrails",
			"desc": "Colorful cosmetic trails to get around fabulously.",
			"jarName": "SuperTrails.jar",
			"configName": "SuperTrails"
		},
		{
			"name": "CustomEnchants",
			"desc": "Custom enchantments and levels!",
			"jarName": "CustomEnchantments.jar",
			"configName": "CustomEnchantments"
		},
		{
			"name": "Citizens",
			"desc": "Create custom and interactive NPCs.\n&cRequires $10 rank to install.\n&cCan cause extreme lag. Lots of free RAM is required!",
			"jarName": "Citizens.jar",
			"configName": "Citizens",
			"requiredRank": "1"
		},
		{
			"name": "McMMO",
			"desc": "RPG experience in Minecraft!\n&cRequires $10 rank to install.",
			"jarName": "mcMMO.jar",
			"configName": "mcMMO",
			"requiredRank": "1"
		},
		{   
			"name": "Factions",
			"desc": "Claim land, build a base and wage war!\n&cRequires $25 rank to install.",
			"jarName": "Factions.jar",
			"configName": "Factions",
			"requiredRank": "2"
		},
		{   
			"name": "Obsidian Breaker",
			"desc": "Allows explosions to break Obsidian!\n&aWorks well with Factions raiding.\n&cRequires $25 rank to install.",
			"jarName": "ObsidianBreaker.jar",
			"configName": "ObsidianBreaker",
			"requiredRank": "2"
		},
		{
			"name": "Sky Block",
			"desc": "Survive on Skyblock islands.\n&cThis plugin requires &nVault&c.",
			"jarName": "askyblock.jar",
			"configName": "ASkyBlock",
			"requiredRank": "2"
		},
		{
			"name": "Towny",
			"desc": "Towny is a versatile, player-controlled land management plugin.",
			"jarName": "Towny.jar",
			"configName": "Towny",
			"requiredRank": "4"
		},
		{
			"name": "TownyChat",
			"desc": "This plugin is required if you want to let Towny modify chat in any way.",
			"jarName": "TownyChat.jar",
			"configName": "TownyChat",
			"requiredRank": "4"
		},
		{
			"name": "Multiverse-Core",
			"desc": "Multi-world management.",
			"jarName": "Multiverse-Core.jar",
			"configName": "Multiverse-Core",
			"requiredRank": "4"
		},
		{
			"name": "VoidWorld",
			"desc": "Create void-worlds with this and Multiverse-Core.",
			"jarName": "VoidWorld.jar",
			"configName": "VoidWorld",
			"requiredRank": "4"
		},
			{
			"name": "PlotSquared",
			"desc": "PlotSquared is a land management plugin.",
			"jarName": "PlotSquared.jar",
			"configName": "PlotSquared",
			"requiredRank": "4"
		}
	]
}
